certbot_dns_domeneshop/__init__.py
certbot_dns_domeneshop/dns_domeneshop.py
certbot_dns_domeneshop-0.2.9.dist-info/LICENSE.txt
certbot_dns_domeneshop-0.2.9.dist-info/METADATA
certbot_dns_domeneshop-0.2.9.dist-info/WHEEL
certbot_dns_domeneshop-0.2.9.dist-info/entry_points.txt
certbot_dns_domeneshop-0.2.9.dist-info/top_level.txt
certbot_dns_domeneshop-0.2.9.dist-info/RECORD
