Metadata-Version: 2.1
Name: certbot-dns-domeneshop
Version: 0.2.9
Summary: Domeneshop Certbot Plugin
Home-page: https://github.com/domeneshop/certbot-dns-domeneshop
Author: Domeneshop AS
Author-email: kundeservice@domeneshop.no
License: Apache License 2.0
Classifier: Environment :: Plugins
Classifier: Intended Audience :: System Administrators
Classifier: Operating System :: POSIX :: Linux
Classifier: Programming Language :: Python
Classifier: Programming Language :: Python :: 3
Classifier: Programming Language :: Python :: 3.4
Classifier: Programming Language :: Python :: 3.5
Classifier: Programming Language :: Python :: 3.6
Classifier: Topic :: Internet :: WWW/HTTP
Classifier: Topic :: Security
Classifier: Topic :: System :: Installation/Setup
Classifier: Topic :: System :: Networking
Classifier: Topic :: System :: Systems Administration
Classifier: Topic :: Utilities
Requires-Python: !=2.*, !=3.0.*, !=3.1.*, !=3.2.*, !=3.3.*
License-File: LICENSE.txt
Requires-Dist: domeneshop (>=0.4.2)
Requires-Dist: acme (>=0.21.1)
Requires-Dist: certbot (>=0.21.1)
Requires-Dist: setuptools
Requires-Dist: zope.interface
Requires-Dist: requests (>=2.21.0)
Provides-Extra: dev
Requires-Dist: black ; extra == 'dev'
Requires-Dist: mypy ; extra == 'dev'
Requires-Dist: prospector ; extra == 'dev'
